__init__.py
data_download.py
eloquentcls.py
eloquentcls-0.0.4.dist-info/METADATA
eloquentcls-0.0.4.dist-info/WHEEL
eloquentcls-0.0.4.dist-info/top_level.txt
eloquentcls-0.0.4.dist-info/RECORD
