Metadata-Version: 2.1
Name: eloquentcls
Version: 0.0.4
Summary: Unimodal Eloquent Classifier
Author: Dr. Shakeel Ahmad Sheikh
Classifier: Programming Language :: Python :: 3.11
Requires-Dist: torch (>=2.0.1)
